plumkdocs/__init__.py
plumkdocs/main.py
plumkdocs-0.0.5.dist-info/LICENSE.txt
plumkdocs-0.0.5.dist-info/METADATA
plumkdocs-0.0.5.dist-info/WHEEL
plumkdocs-0.0.5.dist-info/RECORD
