Metadata-Version: 2.1
Name: plumkdocs
Version: 0.0.5
Summary: Hacky mkdocs documentation for plum-dispatch
License: LGPL-3.0-only
Author: Antonio Stanziola
Author-email: stanziola.antonio@gmail.com
Requires-Python: >=3.9,<4.0
Classifier: Intended Audience :: Education
Classifier: Intended Audience :: Science/Research
Classifier: License :: OSI Approved :: GNU Lesser General Public License v3 (LGPLv3)
Classifier: Programming Language :: Python :: 3
Classifier: Programming Language :: Python :: 3.9
Classifier: Programming Language :: Python :: 3.10
Classifier: Programming Language :: Python :: 3.11
Classifier: Programming Language :: Python :: 3.12
Classifier: Programming Language :: Python :: 3.8
Requires-Dist: griffe (>=0.38.0,<0.39.0)
Requires-Dist: markdown (>=3.5.1,<4.0.0)
Requires-Dist: mkdocs-macros-plugin (>=1.0,<2.0)
Requires-Dist: mkdocs-material (>=9.4,<10.0)
Requires-Dist: mkdocstrings (>=0.24,<0.25)
Requires-Dist: plum-dispatch (>=2,<3)
Project-URL: Bug Tracker, https://github.com/astanziola/plumkdocs/issues
Project-URL: Homepage, https://github.com/astanziola/plumkdocs
